cloudml/CM任务.sh
cloudml/README.md
cloudml/__init__.py
cloudml/config.yaml
cloudml/git_secret.sh
cloudml/sh.sh
conf/__init__.py
conf/cm.conf
conf/mivideo_push/__init__.py
conf/mivideo_push/daily_train_mitv_base_days.sh
conf/mivideo_push/dnn.yml
conf/mivideo_push/dnn_v0.yml
conf/mivideo_push/dnn_v1.yml
conf/mivideo_push/dnn_v11.yml
conf/mivideo_push/mitv_base_online_nn.yaml
conf/mivideo_push/push_mitv_v0_train.yaml
conf/mivideo_push/train.sh
conf/mivideo_push/train_dnn.sh
conf/mivideo_push/train_dnn_v11.sh
conf/mivideo_push/train_v1.sh
ctrzoo/__init__.py
ctrzoo/check_hdfs.py
ctrzoo/check_zk.py
ctrzoo/cli.py
ctrzoo/cms.py
ctrzoo/crazy_run.py
ctrzoo/io_opt_demo.py
ctrzoo/parquet2csv.py
ctrzoo/simbert_vector.py
ctrzoo/test.py
ctrzoo/ann/__init__.py
ctrzoo/ann/ann_create.py
ctrzoo/ann/ann_insert.py
ctrzoo/ann/ann_profile.py
ctrzoo/ann/c4.py
ctrzoo/ann/push_watcher.py
ctrzoo/ann/recall_user.py
ctrzoo/cm/__init__.py
ctrzoo/cm/cm_delete.py
ctrzoo/distributed_training/TF_CONFIG.yml
ctrzoo/distributed_training/__init__.py
ctrzoo/distributed_training/demo.py
ctrzoo/distributed_training/multi_workers.py
ctrzoo/distributed_training/one_multi_card.py
ctrzoo/distributed_training/one_multi_card_cm.py
ctrzoo/distributed_training/one_multi_card_cm_2.py
ctrzoo/distributed_training/cluster_resolver/__init__.py
ctrzoo/distributed_training/cluster_resolver/chief.py
ctrzoo/distributed_training/cluster_resolver/ps.py
ctrzoo/distributed_training/cluster_resolver/worker.py
ctrzoo/experiment/__init__.py
ctrzoo/experiment/ab.py
ctrzoo/experiment/ann_ab.py
ctrzoo/experiment/mivideo_profile_ab.py
ctrzoo/image/__init__.py
ctrzoo/image/img2vec.py
ctrzoo/nlp/__init__.py
ctrzoo/nlp/auto_title.py
ctrzoo/notice/__init__.py
ctrzoo/notice/experiment_expired.py
ctrzoo/profile/__init__.py
ctrzoo/profile/distcp.py
ctrzoo/report/__init__.py
ctrzoo/report/hive_test.py
ctrzoo/report/mysql2hdfs.py
ctrzoo/serving/__init__.py
ctrzoo/serving/ann_app.py
ctrzoo/serving/pingpong.thrift
ctrzoo/serving/server.py
ctrzoo-2021.4.15.20.53.23.dist-info/AUTHORS.rst
ctrzoo-2021.4.15.20.53.23.dist-info/LICENSE
ctrzoo-2021.4.15.20.53.23.dist-info/METADATA
ctrzoo-2021.4.15.20.53.23.dist-info/WHEEL
ctrzoo-2021.4.15.20.53.23.dist-info/entry_points.txt
ctrzoo-2021.4.15.20.53.23.dist-info/top_level.txt
ctrzoo-2021.4.15.20.53.23.dist-info/RECORD
